package_name/__init__.py
KahootSpam-1.2.0.dist-info/METADATA
KahootSpam-1.2.0.dist-info/WHEEL
KahootSpam-1.2.0.dist-info/top_level.txt
KahootSpam-1.2.0.dist-info/RECORD
