Metadata-Version: 2.1
Name: KahootSpam
Version: 1.2.0
Summary: A kahoot api to spam bots
Home-page: https://github.com/someStranger8/kahoot-api
Author: Gage Atkinson, Liam Jenne, Aedan Jones
Author-email: someStranger87@gmail.com
License: UNKNOWN
Platform: UNKNOWN
Classifier: Programming Language :: Python :: 3
Classifier: Operating System :: OS Independent
Requires-Python: >=3.6
